paintnine/__init__.py
paintnine/polygon.py
paintnine-0.0.1.dist-info/LICENSE
paintnine-0.0.1.dist-info/METADATA
paintnine-0.0.1.dist-info/WHEEL
paintnine-0.0.1.dist-info/top_level.txt
paintnine-0.0.1.dist-info/RECORD
